paxstore_open_api_sdk/__init__.py
paxstore_open_api_sdk/paxstore_api_client.py
paxstore_open_api_sdk/terminal_api.py
paxstore_open_api_sdk/utils.py
paxstore_open_api_sdk/dto/__init__.py
paxstore_open_api_sdk/dto/terminal_dto.py
paxstore_open_api_sdk-0.1.2.dist-info/LICENSE
paxstore_open_api_sdk-0.1.2.dist-info/METADATA
paxstore_open_api_sdk-0.1.2.dist-info/WHEEL
paxstore_open_api_sdk-0.1.2.dist-info/top_level.txt
paxstore_open_api_sdk-0.1.2.dist-info/RECORD
