Metadata-Version: 2.1
Name: paxstore-open-api-sdk
Version: 0.1.2
Summary: Cloud open api SDK for customer system to synchronize related data
Home-page: https://github.com/fjamon/paxstore-openapi-python-sdk
Author: François Joseph AMON D''ABY
Author-email: ange_amon@live.fr
License: UNKNOWN
Project-URL: Bug Tracker, https://github.com/fjamon/paxstore-openapi-python-sdk/issues
Platform: UNKNOWN
Classifier: Programming Language :: Python :: 3
Classifier: License :: OSI Approved :: MIT License
Classifier: Operating System :: OS Independent
Requires-Python: >=3.6
License-File: LICENSE
Requires-Dist: requests
